{"topic":"member.action.profile.trait.update","originator":"member-api","timestamp":"2018-02-16T00:00:00","mime-type":"application/json","payload":{"userId":40309264,"handle":"thomaskranitsas","traitId":"basic_info","categoryName":"Basic Info","createdAt":"11/23/18 10:39 AM","updatedBy":40309264,"traits":{"data":[{"handle":"thomaskranitsas","firstName":"Thomas","lastName":"Kranitsas","shortBio":"","country":"United States","primaryInterestInTopcoder":"","currentLocation":"","userId":40309264,"description":"Topcoder Quote updated ","status":"ACTIVE","email":"kranitsasthomas@gmail.com","addresses":[{"streetAddr1":"Garivaldi 50","streetAddr2":"Street addr 2","city":"Karditsa","zip":"43200","type":"HOME","updatedAt":null,"createdAt":null,"createdBy":null,"updatedBy":null}],"homeCountryCode":"USA","competitionCountryCode":"USA","tracks":[]}]},"createdBy":40309264,"updatedAt":"11/23/18 10:39 AM"}}